{
  "resolvedId": "C:/Users/XFXRe/Desktop/Portfolio/node_modules/picomatch/index.js",
  "transforms": [
    {
      "name": "vite:load-fallback",
      "result": "'use strict';\n\nmodule.exports = require('./lib/picomatch');\n",
      "start": 1718972211543,
      "end": 1718972211593,
      "sourcemaps": null
    },
    {
      "name": "vite:css",
      "start": 1718972211593,
      "end": 1718972211593,
      "order": "normal"
    },
    {
      "name": "vite:esbuild",
      "start": 1718972211593,
      "end": 1718972211593,
      "order": "normal"
    },
    {
      "name": "vite:json",
      "start": 1718972211593,
      "end": 1718972211593,
      "order": "normal"
    },
    {
      "name": "vite:worker",
      "start": 1718972211593,
      "end": 1718972211593,
      "order": "normal"
    },
    {
      "name": "vite:define",
      "start": 1718972211593,
      "end": 1718972211593,
      "order": "normal"
    },
    {
      "name": "vite:css-post",
      "start": 1718972211593,
      "end": 1718972211593,
      "order": "normal"
    },
    {
      "name": "vite:build-html",
      "start": 1718972211593,
      "end": 1718972211593,
      "order": "normal"
    },
    {
      "name": "vite:worker-import-meta-url",
      "start": 1718972211593,
      "end": 1718972211593,
      "order": "normal"
    },
    {
      "name": "vite:asset-import-meta-url",
      "start": 1718972211593,
      "end": 1718972211593,
      "order": "normal"
    },
    {
      "name": "commonjs",
      "result": "import * as commonjsHelpers from \"\u0000commonjsHelpers.js\";\nimport require$$0 from \"\\u0000C:/Users/XFXRe/Desktop/Portfolio/node_modules/picomatch/lib/picomatch.js?commonjs-proxy\";\n\n'use strict';\n\nvar picomatch = require$$0;\n\nexport default /*@__PURE__*/commonjsHelpers.getDefaultExportFromCjs(picomatch);\nexport { picomatch as __moduleExports };",
      "start": 1718972211593,
      "end": 1718972211810,
      "order": "normal",
      "sourcemaps": {
        "version": 3,
        "sources": [
          ""
        ],
        "names": [],
        "mappings": ";;;AAAA,YAAY,CAAC;AACb;IACA,SAAc,GAAG,UAA0B"
      }
    },
    {
      "name": "vite:dynamic-import-vars",
      "start": 1718972211810,
      "end": 1718972211810,
      "order": "normal"
    },
    {
      "name": "vite:import-glob",
      "start": 1718972211810,
      "end": 1718972211810,
      "order": "normal"
    },
    {
      "name": "vite:build-import-analysis",
      "start": 1718972211810,
      "end": 1718972211810,
      "order": "normal"
    },
    {
      "name": "vite:reporter",
      "start": 1718972211810,
      "end": 1718972211810,
      "order": "normal"
    }
  ]
}
